yanan_mcp_server_package/__init__.py
yanan_mcp_server_package-0.1.0.dist-info/METADATA
yanan_mcp_server_package-0.1.0.dist-info/WHEEL
yanan_mcp_server_package-0.1.0.dist-info/entry_points.txt
yanan_mcp_server_package-0.1.0.dist-info/RECORD
