Metadata-Version: 2.4
Name: yanan-mcp-server-package
Version: 0.1.0
Summary: Add your description here
Author-email: 彭亚楠 <pengyanan1128@126.com>
Requires-Python: >=3.13
Requires-Dist: mcp[cli]>=1.9.4
